caked/__init__.py
caked/base.py
caked/dataloader.py
caked-0.1.7.dist-info/licenses/LICENSE
caked-0.1.7.dist-info/METADATA
caked-0.1.7.dist-info/WHEEL
caked-0.1.7.dist-info/top_level.txt
caked-0.1.7.dist-info/RECORD
