Metadata-Version: 2.4
Name: CAKED
Version: 0.1.7
Summary: A dataloader abstract package
Author-email: Bea Costa Gomes <bcostagomes@turing.ac.uk>
Project-URL: Homepage, https://github.com/alan-turing-institute/CAKED
Project-URL: Bug Tracker, https://github.com/alan-turing-institute/CAKED/issues
Project-URL: Discussions, https://github.com/alan-turing-institute/CAKED/discussions
Project-URL: Changelog, https://github.com/alan-turing-institute/CAKED/releases
Classifier: Development Status :: 1 - Planning
Classifier: Intended Audience :: Science/Research
Classifier: Intended Audience :: Developers
Classifier: License :: OSI Approved :: MIT License
Classifier: Operating System :: OS Independent
Classifier: Programming Language :: Python
Classifier: Programming Language :: Python :: 3
Classifier: Programming Language :: Python :: 3 :: Only
Classifier: Programming Language :: Python :: 3.8
Classifier: Programming Language :: Python :: 3.9
Classifier: Programming Language :: Python :: 3.10
Classifier: Programming Language :: Python :: 3.11
Classifier: Programming Language :: Python :: 3.12
Classifier: Topic :: Scientific/Engineering
Classifier: Typing :: Typed
Requires-Python: >=3.8
License-File: LICENSE
Requires-Dist: torch
Requires-Dist: numpy
Requires-Dist: pandas
Requires-Dist: mrcfile
Requires-Dist: torchvision
Requires-Dist: scipy
Requires-Dist: pyarrow
Provides-Extra: test
Requires-Dist: pytest>=6; extra == "test"
Requires-Dist: pytest-cov>=3; extra == "test"
Requires-Dist: pre-commit; extra == "test"
Provides-Extra: dev
Requires-Dist: pytest>=6; extra == "dev"
Requires-Dist: pytest-cov>=3; extra == "dev"
Provides-Extra: doc
Requires-Dist: sphinx>=5.0.0; extra == "doc"
Requires-Dist: pydata-sphinx-theme>=0.7; extra == "doc"
Dynamic: license-file
